sunburnt/__init__.py
sunburnt/dates.py
sunburnt/schema.py
sunburnt/search.py
sunburnt/strings.py
sunburnt/sunburnt.py
sunburnt/walktree.py
sunburnt_python3-0.8.1.dist-info/LICENSE
sunburnt_python3-0.8.1.dist-info/METADATA
sunburnt_python3-0.8.1.dist-info/WHEEL
sunburnt_python3-0.8.1.dist-info/top_level.txt
sunburnt_python3-0.8.1.dist-info/RECORD
