Metadata-Version: 2.1
Name: sunburnt-python3
Version: 0.8.1
Summary: Python interface to Solr
Home-page: https://github.com/christopher-im/sunburnt-python3
Author: Chris Murray
Author-email: chris@chrismurray.scot
License: MIT
Keywords: solr
Platform: UNKNOWN
Classifier: Development Status :: 4 - Beta
Classifier: Programming Language :: Python :: 3
Classifier: Intended Audience :: Developers
Classifier: License :: OSI Approved :: MIT License
Classifier: Programming Language :: Python
Classifier: Topic :: Internet :: WWW/HTTP :: Indexing/Search
Classifier: Topic :: Software Development :: Libraries
Requires: lxml
Requires: pytz
Requires: requests
